xdgconfig/__init__.py
xdgconfig/asset.py
xdgconfig/cli_tools/__init__.py
xdgconfig/cli_tools/_argparse.py
xdgconfig/cli_tools/_typer.py
xdgconfig/cli_tools/common.py
xdgconfig/config.py
xdgconfig/config_unix.py
xdgconfig/config_win.py
xdgconfig/defaultdict.py
xdgconfig/exceptions.py
xdgconfig/git.py
xdgconfig/mixins.py
xdgconfig/plugin.py
xdgconfig/serializers/__init__.py
xdgconfig/serializers/_configparser.py
xdgconfig/serializers/_json.py
xdgconfig/serializers/_python.py
xdgconfig/serializers/_toml.py
xdgconfig/serializers/_xml.py
xdgconfig/serializers/_yaml.py
xdgconfig/utils.py
xdgconfig-1.3.0.dist-info/LICENSE
xdgconfig-1.3.0.dist-info/WHEEL
xdgconfig-1.3.0.dist-info/METADATA
xdgconfig-1.3.0.dist-info/RECORD
