Metadata-Version: 2.1
Name: xdgconfig
Version: 1.3.0
Summary: Easy access to `~/.config`
Home-page: https://github.com/Dogeek/xdgconfig
License: MIT
Author: Dogeek
Author-email: Dogeek@users.noreply.github.com
Requires-Python: >=3.7,<4.0
Classifier: Development Status :: 4 - Beta
Classifier: Intended Audience :: Developers
Classifier: License :: OSI Approved :: MIT License
Classifier: Operating System :: Microsoft :: Windows
Classifier: Operating System :: POSIX
Classifier: Programming Language :: Python :: 3
Classifier: Programming Language :: Python :: 3 :: Only
Classifier: Programming Language :: Python :: 3.10
Classifier: Programming Language :: Python :: 3.7
Classifier: Programming Language :: Python :: 3.8
Classifier: Programming Language :: Python :: 3.9
Classifier: Topic :: Software Development :: Libraries
Provides-Extra: jsonc
Provides-Extra: toml
Provides-Extra: xml
Provides-Extra: yaml
Requires-Dist: mergedeep (>=1.3.4,<2.0.0)
Project-URL: Documentation, https://xdgconfig.readthedocs.io
Project-URL: Repository, https://github.com/Dogeek/xdgconfig
